pytest_icdiff.py
pytest_icdiff-0.8.dist-info/LICENSE
pytest_icdiff-0.8.dist-info/METADATA
pytest_icdiff-0.8.dist-info/WHEEL
pytest_icdiff-0.8.dist-info/entry_points.txt
pytest_icdiff-0.8.dist-info/top_level.txt
pytest_icdiff-0.8.dist-info/RECORD
