Metadata-Version: 2.1
Name: pytest-icdiff
Version: 0.8
Summary: use icdiff for better error messages in pytest assertions
Home-page: https://github.com/hjwp/pytest-icdiff
Author: Harry Percival
Author-email: obeythetestinggoat@gmail.com
Maintainer: Harry Percival
Maintainer-email: obeythetestinggoat@gmail.com
License: Unlicense
Classifier: Development Status :: 4 - Beta
Classifier: Framework :: Pytest
Classifier: Intended Audience :: Developers
Classifier: Topic :: Software Development :: Testing
Classifier: Programming Language :: Python
Classifier: Programming Language :: Python :: 3.7
Classifier: Programming Language :: Python :: 3.8
Classifier: Programming Language :: Python :: 3.9
Classifier: Programming Language :: Python :: 3.10
Classifier: Programming Language :: Python :: 3.11
Classifier: Operating System :: OS Independent
Classifier: License :: Public Domain
Requires-Python: >=3.7
License-File: LICENSE
Requires-Dist: pytest
Requires-Dist: icdiff
Requires-Dist: pprintpp
